iseries/__init__.py
iseries/iseries.py
iseries-1.0.dist-info/METADATA
iseries-1.0.dist-info/WHEEL
iseries-1.0.dist-info/top_level.txt
iseries-1.0.dist-info/RECORD
